bloby/BlobDetector.py
bloby/BlobMetrics.py
bloby/BossDataFetcher.py
bloby/IngestTifStack.py
bloby/__init__.py
bloby/bossmeta.py
bloby/util.py
bloby-1.2.1.dist-info/METADATA
bloby-1.2.1.dist-info/RECORD
bloby-1.2.1.dist-info/WHEEL
bloby-1.2.1.dist-info/entry_points.txt
bloby-1.2.1.dist-info/top_level.txt
